setup.py
asyncmongoorm/__init__.py
asyncmongoorm/bson_json.py
asyncmongoorm/collection.py
asyncmongoorm/field.py
asyncmongoorm/manager.py
asyncmongoorm/session.py
asyncmongoorm/signal.py
asyncmongoorm_je.egg-info/PKG-INFO
asyncmongoorm_je.egg-info/SOURCES.txt
asyncmongoorm_je.egg-info/dependency_links.txt
asyncmongoorm_je.egg-info/top_level.txt