Metadata-Version: 1.1
Name: asyncmongoorm-je
Version: 0.3.7
Summary: asyncmongoorm
Home-page: http://github.com/marcelnicolay/asyncmongoorm
Author: Marcel Nicolay
Author-email: marcel.nicolay@gmail.com
License: OSI
Keywords: asyncmongo,tornado,torneira
Platform: UNKNOWN
Classifier: Development Status :: 4 - Beta
Classifier: Intended Audience :: Developers
Classifier: License :: OSI Approved
Classifier: Natural Language :: English
Classifier: Natural Language :: Portuguese (Brazilian)
Classifier: Operating System :: POSIX :: Linux
Classifier: Programming Language :: Python :: 2.5
Classifier: Programming Language :: Python :: 2.6
Classifier: Topic :: Software Development :: Libraries :: Application Frameworks
Requires: pymongo (>=2.1)
Requires: tornado (>=2.1.1)
Requires: simplexml (>=0.1.4)
